README.md
setup.py
biketrauma/__init__.py
biketrauma/io/Load_db.py
biketrauma/io/__init__.py
biketrauma/preprocess/__init2__.py
biketrauma/preprocess/format_date.py
biketrauma/preprocess/get_accident.py
biketrauma/vis/__init__.py
biketrauma/vis/plot_location.py
biketrauma_ng.egg-info/PKG-INFO
biketrauma_ng.egg-info/SOURCES.txt
biketrauma_ng.egg-info/dependency_links.txt
biketrauma_ng.egg-info/not-zip-safe
biketrauma_ng.egg-info/top_level.txt