Metadata-Version: 1.0
Name: biketrauma-ng
Version: 0.0.1
Summary: Visualization of a bicycle accident db
Home-page: https://github.com/goujilinouhaila-coder/Bike_trauma.git
Author: Goujili Nouhaila
Author-email: goujilinouhaila@gmail.com
License: MIT
Platform: UNKNOWN
